mds_project_durationcolumn-4.8.0.dist-info/METADATA
mds_project_durationcolumn-4.8.0.dist-info/RECORD
mds_project_durationcolumn-4.8.0.dist-info/WHEEL
mds_project_durationcolumn-4.8.0.dist-info/entry_points.txt
mds_project_durationcolumn-4.8.0.dist-info/top_level.txt
trytond/modules/project_durationcolumn/README.rst
trytond/modules/project_durationcolumn/__init__.py
trytond/modules/project_durationcolumn/tryton.cfg
trytond/modules/project_durationcolumn/versiondep.txt
trytond/modules/project_durationcolumn/work.xml
trytond/modules/project_durationcolumn/view/work_tree.xml
